rpc_wrap/__api.py
rpc_wrap/__init__.py
rpc_wrap/cli.py
rpc_wrap/flask.py
rpc_wrap/pyodide.py
rpc_wrap/sample.py
rpc_wrap-0.3.0.dist-info/entry_points.txt
rpc_wrap-0.3.0.dist-info/WHEEL
rpc_wrap-0.3.0.dist-info/METADATA
rpc_wrap-0.3.0.dist-info/RECORD
