Metadata-Version: 2.1
Name: rpc-wrap
Version: 0.3.0
Summary: 
Author: Kaj Siebert
Author-email: kaj@k-si.com
Requires-Python: >=3.9,<4.0
Classifier: Programming Language :: Python :: 3
Classifier: Programming Language :: Python :: 3.9
Classifier: Programming Language :: Python :: 3.10
Classifier: Programming Language :: Python :: 3.11
Provides-Extra: cli
Provides-Extra: flask
Requires-Dist: click (>=8.1.3,<9.0.0); extra == "cli"
Requires-Dist: click-log (>=0.4.0,<0.5.0); extra == "cli"
Requires-Dist: flask (>=2.2.2,<3.0.0); extra == "flask"
Requires-Dist: flask-cors (>=3.0.10,<4.0.0); extra == "flask"
Requires-Dist: rich (>=12.6.0,<13.0.0); extra == "cli"
Requires-Dist: setuptools (>=62.0.0,<63.0.0)
